TOPSIS_Package/__init__.py
TOPSIS_Package-0.0.1.dist-info/LICENSE.txt
TOPSIS_Package-0.0.1.dist-info/METADATA
TOPSIS_Package-0.0.1.dist-info/WHEEL
TOPSIS_Package-0.0.1.dist-info/top_level.txt
TOPSIS_Package-0.0.1.dist-info/RECORD
