Metadata-Version: 2.1
Name: TOPSIS-Package
Version: 0.0.1
Summary: Python package for TOPSIS implementation using Vector Normalization.
Home-page: https://github.com/jsunishka/TOPSIS_package
Author: Sunishka Jain
Author-email: sunishkajain15@gmail.com
License: UNKNOWN
Platform: UNKNOWN
Classifier: Programming Language :: Python :: 3
Classifier: License :: OSI Approved :: MIT License
Classifier: Operating System :: OS Independent
Requires-Python: >=3.6
